ZetcodeRubyJiaochengChuyiFix1/README.md
ZetcodeRubyJiaochengChuyiFix1/__init__.py
ZetcodeRubyJiaochengChuyiFix1/__main__.py
ZetcodeRubyJiaochengChuyiFix1/file.epub
ZetcodeRubyJiaochengChuyiFix1/index.html
ZetcodeRubyJiaochengChuyiFix1/css/__init__.py
ZetcodeRubyJiaochengChuyiFix1/css/annotations.css
ZetcodeRubyJiaochengChuyiFix1/css/main.css
ZetcodeRubyJiaochengChuyiFix1/css/normalize.css
ZetcodeRubyJiaochengChuyiFix1/css/popup.css
ZetcodeRubyJiaochengChuyiFix1/font/__init__.py
ZetcodeRubyJiaochengChuyiFix1/font/fontello.eot
ZetcodeRubyJiaochengChuyiFix1/font/fontello.svg
ZetcodeRubyJiaochengChuyiFix1/font/fontello.ttf
ZetcodeRubyJiaochengChuyiFix1/font/fontello.woff
ZetcodeRubyJiaochengChuyiFix1/img/__init__.py
ZetcodeRubyJiaochengChuyiFix1/img/annotator-glyph-sprite.png
ZetcodeRubyJiaochengChuyiFix1/img/annotator-icon-sprite.png
ZetcodeRubyJiaochengChuyiFix1/img/apple-touch-icon.png
ZetcodeRubyJiaochengChuyiFix1/img/cancelfullscreen.png
ZetcodeRubyJiaochengChuyiFix1/img/close.png
ZetcodeRubyJiaochengChuyiFix1/img/fullscreen.png
ZetcodeRubyJiaochengChuyiFix1/img/loader.gif
ZetcodeRubyJiaochengChuyiFix1/img/menu-icon.png
ZetcodeRubyJiaochengChuyiFix1/img/save.png
ZetcodeRubyJiaochengChuyiFix1/img/saved.png
ZetcodeRubyJiaochengChuyiFix1/img/settings-s.png
ZetcodeRubyJiaochengChuyiFix1/img/settings.png
ZetcodeRubyJiaochengChuyiFix1/img/star.png
ZetcodeRubyJiaochengChuyiFix1/js/__init__.py
ZetcodeRubyJiaochengChuyiFix1/js/epub.js
ZetcodeRubyJiaochengChuyiFix1/js/epub.min.js
ZetcodeRubyJiaochengChuyiFix1/js/epub.min.map
ZetcodeRubyJiaochengChuyiFix1/js/hooks.min.js
ZetcodeRubyJiaochengChuyiFix1/js/hooks.min.map
ZetcodeRubyJiaochengChuyiFix1/js/reader.js
ZetcodeRubyJiaochengChuyiFix1/js/reader.js.map
ZetcodeRubyJiaochengChuyiFix1/js/reader.min.js
ZetcodeRubyJiaochengChuyiFix1/js/reader.min.map
ZetcodeRubyJiaochengChuyiFix1/js/hooks/__init__.py
ZetcodeRubyJiaochengChuyiFix1/js/hooks/extensions/__init__.py
ZetcodeRubyJiaochengChuyiFix1/js/hooks/extensions/highlight.js
zetcode_ruby_jiaocheng_chuyi_fix1-2025.3.24.0.dist-info/METADATA
zetcode_ruby_jiaocheng_chuyi_fix1-2025.3.24.0.dist-info/WHEEL
zetcode_ruby_jiaocheng_chuyi_fix1-2025.3.24.0.dist-info/entry_points.txt
zetcode_ruby_jiaocheng_chuyi_fix1-2025.3.24.0.dist-info/top_level.txt
zetcode_ruby_jiaocheng_chuyi_fix1-2025.3.24.0.dist-info/RECORD
